{
  "required": false,
  "minVersion": "0.8",
  "package": "io.yukkuric.mnaop.mixin",
  "compatibilityLevel": "JAVA_8",
  "refmap": "mnaoverpowered.refmap.json",
  "plugin": "io.yukkuric.mnaop.mixin_interface.MNAOPMixinPlugin",
  "mixins": [
    "MixinCastingResource",
    "MixinConstructMilkCow",
    "MixinLodestarMenu",
    "MixinRuneForge",
    "MixinWellspringNode",
    "MixinWellspringSystem",
    "computercraft.AccessorInventoryMethods",
    "fixes.FixItemFilterWithHollow",
    "fixes.FixManaPylon",
    "fixes.FixSpellAdjusterRegisterLock",
    "fixes.FixTieredRecipeSorter",
    "magichem.AccessorConstructProvideMateria",
    "magichem.AccessorPrimeAggregator",
    "magichem.MixinInstantConstructShlorper",
    "magichem.MixinInstantConstructShlorper$MateriaSort",
    "magichem.MixinOrreryLimitBreak",
    "magichem.MixinPowerCircle",
    "magichem.ext.MixinCircleFabrication",
    "magichem.ext.MixinCircleFabrication$Router",
    "magichem.ext.MixinClearRecipe",
    "magichem.ext.MixinLastUserExtended",
    "magichem.ext.MixinLastUserExtended$Menu_Style1",
    "magichem.ext.MixinLastUserExtended$Menu_Style2",
    "magichem.ext.MixinNexusLastUser"
  ],
  "client": [
    "AccessorLodestarNode",
    "MixinLodestarGUI",
    "magichem.MixinPowerCircle$Screen"
  ],
  "injectors": {
    "defaultRequire": 1
  },
  "overwrites": {
    "requireAnnotations": true
  }
}
